tinysmith/__init__.py
tinysmith/agent/__init__.py
tinysmith/agent/agent.py
tinysmith/agent/strategies/planner_reviewer_executor/__init__.py
tinysmith/agent/strategies/planner_reviewer_executor/prompting.py
tinysmith/agent/strategies/planner_reviewer_executor/templates/executor.prompt
tinysmith/agent/strategies/planner_reviewer_executor/templates/executor_new.prompt
tinysmith/agent/strategies/planner_reviewer_executor/templates/executor_new_user.prompt
tinysmith/agent/strategies/planner_reviewer_executor/templates/few_shot_executor.prompt
tinysmith/agent/strategies/planner_reviewer_executor/templates/few_shot_executor_new.prompt
tinysmith/agent/strategies/planner_reviewer_executor/templates/master.prompt
tinysmith/agent/strategies/planner_reviewer_executor/templates/planner.prompt
tinysmith/agent/strategies/planner_reviewer_executor/templates/reviewer.prompt
tinysmith/agent/strategies/planner_reviewer_executor/transition.py
tinysmith/agent/strategies/planner_reviewer_executor/utils.py
tinysmith/agent/strategies/reflexion/__init__.py
tinysmith/agent/strategies/reflexion/prompting.py
tinysmith/agent/strategies/reflexion/templates/actor_system.prompt
tinysmith/agent/strategies/reflexion/templates/actor_user.prompt
tinysmith/agent/strategies/reflexion/templates/few_shot.prompt
tinysmith/agent/strategies/reflexion/templates/few_shot_simple.prompt
tinysmith/agent/strategies/reflexion/templates/reflector_system.prompt
tinysmith/agent/strategies/reflexion/templates/reflector_user.prompt
tinysmith/agent/strategies/reflexion/transition.py
tinysmith/agent/strategies/single_agent/__init__.py
tinysmith/agent/strategies/single_agent/prompting.py
tinysmith/agent/strategies/single_agent/templates/few_shot.prompt
tinysmith/agent/strategies/single_agent/templates/few_shot_simple.prompt
tinysmith/agent/strategies/single_agent/templates/system.prompt
tinysmith/agent/strategies/single_agent/templates/user.prompt
tinysmith/agent/strategies/single_agent/transition.py
tinysmith-0.9.1.dist-info/WHEEL
tinysmith-0.9.1.dist-info/METADATA
tinysmith-0.9.1.dist-info/LICENSE.txt
tinysmith-0.9.1.dist-info/RECORD
