Metadata-Version: 2.1
Name: tinysmith
Version: 0.9.1
Summary: TinyAgentSmith (tinysmith) is a tiny, modular multi-agent LLM framework. It is designed to be lightweight and simple to use, while providing a flexible and extensible platform for quickly iterating on multi-agent algorithms.
License: GPL-3.0-or-later
Author: J. Florian Kimmes
Author-email: tinysmith@jfkimmes.eu
Requires-Python: >=3.11,<4.0
Classifier: License :: OSI Approved :: GNU General Public License v3 or later (GPLv3+)
Classifier: Programming Language :: Python :: 3
Classifier: Programming Language :: Python :: 3.11
Requires-Dist: distance (>=0.1.3,<0.2.0)
Requires-Dist: groq (>=0.16.0,<0.17.0)
Requires-Dist: mistralai (>=1.5.0,<2.0.0)
Requires-Dist: openai (>=1.60.2,<2.0.0)
Requires-Dist: rich (>=13.9.4,<14.0.0)
